<?xml version="1.0" encoding="UTF-8"?>
<transformationModule xmlns="http://www.wldelft.nl/fews" xmlns:xsi="http://www.w3.org/2001/XMLSchema-instance" xsi:schemaLocation="http://www.wldelft.nl/fews http://chps1/schemas/transformationModule.xsd" version="1.0">
	<variable>
		<variableId>ALSQ9GL_SQIN_6</variableId>
		<timeSeriesSet>
			<moduleInstanceId>UNITHG_ALSQ9_ALSQ9GL_UpdateStates</moduleInstanceId>
			<valueType>scalar</valueType>
			<parameterId>SQIN</parameterId>
			<locationId>ALSQ9GL</locationId>
			<timeSeriesType>simulated historical</timeSeriesType>
			<timeStep unit="hour" multiplier="6"/>
			<relativeViewPeriod unit="hour" start="-240" startOverrulable="true" end="0"/>
			<readWriteMode>read only</readWriteMode>
		</timeSeriesSet>
	</variable>
	<variable>
		<variableId>ALSQ9UPR_SQIN_6</variableId>
		<timeSeriesSet>
			<moduleInstanceId>UNITHG_ALSQ9_ALSQ9UPR_UpdateStates</moduleInstanceId>
			<valueType>scalar</valueType>
			<parameterId>SQIN</parameterId>
			<locationId>ALSQ9UPR</locationId>
			<timeSeriesType>simulated historical</timeSeriesType>
			<timeStep unit="hour" multiplier="6"/>
			<relativeViewPeriod unit="hour" start="-240" startOverrulable="true" end="0"/>
			<readWriteMode>read only</readWriteMode>
		</timeSeriesSet>
	</variable>
	<variable>
		<variableId>ALSQ9LWR_SQIN_6</variableId>
		<timeSeriesSet>
			<moduleInstanceId>UNITHG_ALSQ9_ALSQ9LWR_UpdateStates</moduleInstanceId>
			<valueType>scalar</valueType>
			<parameterId>SQIN</parameterId>
			<locationId>ALSQ9LWR</locationId>
			<timeSeriesType>simulated historical</timeSeriesType>
			<timeStep unit="hour" multiplier="6"/>
			<relativeViewPeriod unit="hour" start="-240" startOverrulable="true" end="0"/>
			<readWriteMode>read only</readWriteMode>
		</timeSeriesSet>
	</variable>
	<variable>
		<variableId>DEZQ9RTD_SQIN_6</variableId>
		<timeSeriesSet>
			<moduleInstanceId>LAGK_ALSQ9_DEZQ9_UpdateStates</moduleInstanceId>
			<valueType>scalar</valueType>
			<parameterId>SQIN</parameterId>
			<locationId>DEZQ9RTD</locationId>
			<timeSeriesType>simulated historical</timeSeriesType>
			<timeStep unit="hour" multiplier="6"/>
			<relativeViewPeriod unit="hour" start="-240" startOverrulable="true" end="0"/>
			<readWriteMode>read only</readWriteMode>
		</timeSeriesSet>
	</variable>
	<variable>
		<variableId>ALSQ9_SQIN_6</variableId>
		<timeSeriesSet>
			<moduleInstanceId>ADDSUB_ALSQ9_ALSQ9GL_UpdateStates</moduleInstanceId>
			<valueType>scalar</valueType>
			<parameterId>SQIN</parameterId>
			<locationId>ALSQ9</locationId>
			<timeSeriesType>simulated historical</timeSeriesType>
			<timeStep unit="hour" multiplier="6"/>
			<relativeViewPeriod unit="hour" start="-240" startOverrulable="true" end="0"/>
			<readWriteMode>add originals</readWriteMode>
		</timeSeriesSet>
	</variable>
	<transformation id="ALSQ9GL">
		<user>
			<simple>
				<expression>max(max(max((max(+ALSQ9GL_SQIN_6+0.000E+00,0))+ALSQ9UPR_SQIN_6,0)+ALSQ9LWR_SQIN_6,0)+DEZQ9RTD_SQIN_6,0)</expression>
				<outputVariable>
					<variableId>ALSQ9_SQIN_6</variableId>
				</outputVariable>
			</simple>
		</user>
	</transformation>
</transformationModule>