<?xml version="1.0" encoding="UTF-8"?>
<workflow xmlns="http://www.wldelft.nl/fews" xmlns:xsi="http://www.w3.org/2001/XMLSchema-instance" xsi:schemaLocation="http://www.wldelft.nl/fews http://chps1/schemas/workflow.xsd" version="1.1">
	<activity>
		<runIndependent>false</runIndependent>
		<moduleInstanceId>RSNWELEV_CTSA2_CTSA2RSN_Forecast</moduleInstanceId>
	</activity>
	<activity>
		<runIndependent>false</runIndependent>
		<moduleInstanceId>SNOW17_CTSA2_CTSA2UPR_Forecast</moduleInstanceId>
	</activity>
	<activity>
		<runIndependent>false</runIndependent>
		<moduleInstanceId>SNOW17_CTSA2_CTSA2LWR_Forecast</moduleInstanceId>
	</activity>
	<activity>
		<runIndependent>false</runIndependent>
		<moduleInstanceId>SACSMA_CTSA2_CTSA2UPR_Forecast</moduleInstanceId>
	</activity>
	<activity>
		<runIndependent>false</runIndependent>
		<moduleInstanceId>SACSMA_CTSA2_CTSA2LWR_Forecast</moduleInstanceId>
	</activity>
	<activity>
		<runIndependent>false</runIndependent>
		<moduleInstanceId>SETTS_CTSA2_CTSA2UPR_Forecast</moduleInstanceId>
	</activity>
	<activity>
		<runIndependent>false</runIndependent>
		<moduleInstanceId>UNITHG_CTSA2_CTSA2UPR_Forecast</moduleInstanceId>
	</activity>
	<activity>
		<runIndependent>false</runIndependent>
		<moduleInstanceId>SETTS_CTSA2_CTSA2LWR_Forecast</moduleInstanceId>
	</activity>
	<activity>
		<runIndependent>false</runIndependent>
		<moduleInstanceId>UNITHG_CTSA2_CTSA2LWR_Forecast</moduleInstanceId>
	</activity>
	<activity>
		<runIndependent>false</runIndependent>
		<moduleInstanceId>SETTS_CTSA2_COOA2RTD_Forecast</moduleInstanceId>
	</activity>
	<activity>
		<runIndependent>false</runIndependent>
		<moduleInstanceId>LAGK_CTSA2_COOA2_Forecast</moduleInstanceId>
	</activity>
	<activity>
		<runIndependent>false</runIndependent>
		<moduleInstanceId>ADDSUB_CTSA2_CTSA2UPR_Forecast</moduleInstanceId>
	</activity>
	<activity>
		<runIndependent>false</runIndependent>
		<moduleInstanceId>ADDSUB_CTSA2_COOA2RTD_Forecast</moduleInstanceId>
	</activity>
	<activity>
		<runIndependent>false</runIndependent>
		<moduleInstanceId>CHANGET_CTSA2_CTSA2USW_Forecast</moduleInstanceId>
	</activity>
	<activity>
		<runIndependent>false</runIndependent>
		<moduleInstanceId>CHANGET_CTSA2_CTSA2LSW_Forecast</moduleInstanceId>
	</activity>
	<activity>
		<runIndependent>false</runIndependent>
		<moduleInstanceId>CHANGET_CTSA2_CTSA2USC_Forecast</moduleInstanceId>
	</activity>
	<activity>
		<runIndependent>false</runIndependent>
		<moduleInstanceId>CHANGET_CTSA2_CTSA2LSC_Forecast</moduleInstanceId>
	</activity>
	<activity>
		<runIndependent>false</runIndependent>
		<moduleInstanceId>CHANGET_CTSA2_CTSA2MAT_Forecast</moduleInstanceId>
	</activity>
	<activity>
		<runIndependent>false</runIndependent>
		<moduleInstanceId>CHANGET_CTSA2_CTSA2RSN_Forecast</moduleInstanceId>
	</activity>
</workflow>