<?xml version="1.0" encoding="UTF-8"?>
<workflow xmlns="http://www.wldelft.nl/fews" xmlns:xsi="http://www.w3.org/2001/XMLSchema-instance" xsi:schemaLocation="http://www.wldelft.nl/fews http://chps1/schemas/workflow.xsd" version="1.1">
	<activity>
		<runIndependent>false</runIndependent>
		<moduleInstanceId>RSNWELEV_TONA2_TONA2RSN_UpdateStates</moduleInstanceId>
	</activity>
	<activity>
		<runIndependent>false</runIndependent>
		<moduleInstanceId>SNOW17_TONA2_TONA2GL_UpdateStates</moduleInstanceId>
	</activity>
	<activity>
		<runIndependent>false</runIndependent>
		<moduleInstanceId>SNOW17_TONA2_TONA2UPR_UpdateStates</moduleInstanceId>
	</activity>
	<activity>
		<runIndependent>false</runIndependent>
		<moduleInstanceId>SNOW17_TONA2_TONA2LWR_UpdateStates</moduleInstanceId>
	</activity>
	<activity>
		<runIndependent>false</runIndependent>
		<moduleInstanceId>GLACIER_TONA2_TONA2GL_UpdateStates</moduleInstanceId>
	</activity>
	<activity>
		<runIndependent>false</runIndependent>
		<moduleInstanceId>SACSMA_TONA2_TONA2UPR_UpdateStates</moduleInstanceId>
	</activity>
	<activity>
		<runIndependent>false</runIndependent>
		<moduleInstanceId>SACSMA_TONA2_TONA2LWR_UpdateStates</moduleInstanceId>
	</activity>
	<activity>
		<runIndependent>false</runIndependent>
		<moduleInstanceId>SETTS_TONA2_TONA2GL_UpdateStates</moduleInstanceId>
	</activity>
	<activity>
		<runIndependent>false</runIndependent>
		<moduleInstanceId>UNITHG_TONA2_TONA2GL_UpdateStates</moduleInstanceId>
	</activity>
	<activity>
		<runIndependent>false</runIndependent>
		<moduleInstanceId>SETTS_TONA2_TONA2UPR_UpdateStates</moduleInstanceId>
	</activity>
	<activity>
		<runIndependent>false</runIndependent>
		<moduleInstanceId>UNITHG_TONA2_TONA2UPR_UpdateStates</moduleInstanceId>
	</activity>
	<activity>
		<runIndependent>false</runIndependent>
		<moduleInstanceId>SETTS_TONA2_TONA2LWR_UpdateStates</moduleInstanceId>
	</activity>
	<activity>
		<runIndependent>false</runIndependent>
		<moduleInstanceId>UNITHG_TONA2_TONA2LWR_UpdateStates</moduleInstanceId>
	</activity>
	<activity>
		<runIndependent>false</runIndependent>
		<moduleInstanceId>ADDSUB_TONA2_TONA2GL_UpdateStates</moduleInstanceId>
	</activity>
	<activity>
		<runIndependent>false</runIndependent>
		<moduleInstanceId>SETTS_TONA2_TONA2SQ_UpdateStates</moduleInstanceId>
	</activity>
	<activity>
		<runIndependent>false</runIndependent>
		<moduleInstanceId>LAGK_TONA2_TON_LAKE_UpdateStates</moduleInstanceId>
	</activity>
	<activity>
		<runIndependent>false</runIndependent>
		<moduleInstanceId>STAGEQ_TONA2_TONA2OB6_UpdateStates</moduleInstanceId>
	</activity>
	<activity>
		<runIndependent>false</runIndependent>
		<moduleInstanceId>STAGEQ_TONA2_TONA2SIM_UpdateStates</moduleInstanceId>
	</activity>
	<activity>
		<runIndependent>false</runIndependent>
		<moduleInstanceId>SETTS_TONA2_TONA2QN_UpdateStates</moduleInstanceId>
	</activity>
	<activity>
		<runIndependent>false</runIndependent>
		<moduleInstanceId>ADJUSTQ_TONA2_TONA2ADJ_UpdateStates</moduleInstanceId>
	</activity>
	<activity>
		<runIndependent>false</runIndependent>
		<moduleInstanceId>STAGEQ_TONA2_TONA2ADJ_UpdateStates</moduleInstanceId>
	</activity>
	<activity>
		<runIndependent>false</runIndependent>
		<moduleInstanceId>CHANGET_TONA2_TONA2GSW_UpdateStates</moduleInstanceId>
	</activity>
	<activity>
		<runIndependent>false</runIndependent>
		<moduleInstanceId>CHANGET_TONA2_TONA2USW_UpdateStates</moduleInstanceId>
	</activity>
	<activity>
		<runIndependent>false</runIndependent>
		<moduleInstanceId>CHANGET_TONA2_TONA2LSW_UpdateStates</moduleInstanceId>
	</activity>
	<activity>
		<runIndependent>false</runIndependent>
		<moduleInstanceId>CHANGET_TONA2_TONA2GSC_UpdateStates</moduleInstanceId>
	</activity>
	<activity>
		<runIndependent>false</runIndependent>
		<moduleInstanceId>CHANGET_TONA2_TONA2USC_UpdateStates</moduleInstanceId>
	</activity>
	<activity>
		<runIndependent>false</runIndependent>
		<moduleInstanceId>CHANGET_TONA2_TONA2LSC_UpdateStates</moduleInstanceId>
	</activity>
	<activity>
		<runIndependent>false</runIndependent>
		<moduleInstanceId>CHANGET_TONA2_TONA2MAT_UpdateStates</moduleInstanceId>
	</activity>
	<activity>
		<runIndependent>false</runIndependent>
		<moduleInstanceId>CHANGET_TONA2_TONA2RSN_UpdateStates</moduleInstanceId>
	</activity>
</workflow>