<?xml version="1.0" encoding="UTF-8"?>
<transformationModule xmlns="http://www.wldelft.nl/fews" xmlns:xsi="http://www.w3.org/2001/XMLSchema-instance" xsi:schemaLocation="http://www.wldelft.nl/fews http://chps1/schemas/transformationModule.xsd" version="1.0">
	<!-- input variables - obs precip -->
	<variable>
		<variableId>PP_POLM8</variableId>
		<timeSeriesSet>
			<moduleInstanceId>ImportSHEF</moduleInstanceId>
			<valueType>scalar</valueType>
			<parameterId>PPF06</parameterId>
			<locationId>POLM8</locationId>
			<timeSeriesType>external forecasting</timeSeriesType>
			<timeStep unit="hour" multiplier="6"/>
			<relativeViewPeriod unit="hour" start="0" startOverrulable="true" end="240" endOverrulable="true"/>
			<readWriteMode>read only</readWriteMode>
		</timeSeriesSet>
	</variable>
	<variable>
		<variableId>PP_FNEQ2</variableId>
		<timeSeriesSet>
			<moduleInstanceId>ImportSHEF</moduleInstanceId>
			<valueType>scalar</valueType>
			<parameterId>PPF06</parameterId>
			<locationId>FNEQ2</locationId>
			<timeSeriesType>external forecasting</timeSeriesType>
			<timeStep unit="hour" multiplier="6"/>
			<relativeViewPeriod unit="hour" start="0" startOverrulable="true" end="240" endOverrulable="true"/>
			<readWriteMode>read only</readWriteMode>
		</timeSeriesSet>
	</variable>
	<variable>
		<variableId>MAP_FCFM8U</variableId>
		<timeSeriesSet>
			<moduleInstanceId>FMAPW_PreProcessing_PPF06</moduleInstanceId>
			<valueType>scalar</valueType>
			<parameterId>FMAPW</parameterId>
			<locationId>FCFM8U</locationId>
			<timeSeriesType>external forecasting</timeSeriesType>
			<timeStep unit="hour" multiplier="6"/>
			<relativeViewPeriod unit="hour" start="0" startOverrulable="true" end="240" endOverrulable="true"/>
			<readWriteMode>add originals</readWriteMode>
		</timeSeriesSet>
	</variable>
	<!-- transformations -->
	<transformation id="FCFM8U">
		<user>
			<simple>
				<expression>+(PP_FNEQ2*.67)+(PP_POLM8*1.)</expression>
				<outputVariable>
					<variableId>MAP_FCFM8U</variableId>
				</outputVariable>
			</simple>
		</user>
	</transformation>
</transformationModule>